prototag/__init__.py
prototag/cli.py
prototag/prototag.py
prototag/selector.py
prototag-0.1.3.dist-info/DESCRIPTION.rst
prototag-0.1.3.dist-info/METADATA
prototag-0.1.3.dist-info/RECORD
prototag-0.1.3.dist-info/WHEEL
prototag-0.1.3.dist-info/entry_points.txt
prototag-0.1.3.dist-info/metadata.json
prototag-0.1.3.dist-info/top_level.txt
